HW4/LAB-02/lab2.v
// pipelined fast multiplier
module mult_fast(
	output reg[7:0] P,  // product
	input[3:0] A, B,    // multiplicand and multiplier
	input clk		    // clock (posedge)
	);
	// stage 0 (input)
	reg[3:0] a_s0, b_s0;
	always @(posedge clk) begin
		a_s0 <= A;
		b_s0 <= B;
	end
	// stage 1: sum each two rows of partial products
	wire[3:0] pp0 = a_s0 & {4{b_s0[0]}}; // ignore the delays of AND gates
	wire[4:1] pp1 = a_s0 & {4{b_s0[1]}}; // ignore the delays of AND gates
	wire[5:2] pp2 = a_s0 & {4{b_s0[2]}}; // ignore the delays of AND gates
	wire[6:3] pp3 = a_s0 & {4{b_s0[3]}}; // ignore the delays of AND gates
	reg[5:1] sum1;
	always @(pp0, pp1)
		sum1[5:1] <= #7 pp0[3:1] + pp1[4:1]; // delay of the 4-bit adder
	reg[7:3] sum3;
	always @(pp2, pp3)
		sum3[7:3] <= #7 pp2[5:3] + pp3[6:3]; // delay of the 4-bit adder
	reg[5:0] sum1_s1;
	reg[7:2] sum3_s1;
	always @(posedge clk) begin
		sum1_s1 <= {sum1, pp0[0]};
		sum3_s1 <= {sum3, pp2[2]};
	end
	// stage 2 (outout)
	reg[7:2] sum2;
	always @(sum1_s1, sum3_s1)
		sum2[7:2] <= #8 sum1_s1[5:2] + sum3_s1[7:2]; // delay of the 6-bit adder
	always @(posedge clk) begin
		P <= {sum2, sum1_s1[1:0]};
	end
endmodule

// test bench
module mult_tb();
	// dump
	initial begin
		$dumpfile("lab2.vcd");
		$dumpvars(0, mult_tb);
	end
	reg clock = 1;
	always
		#4 clock <= ~clock;		// invert the clock every 4 ticks (so the clock cycle is 8 ticks)
	// multiplier
	reg[3:0] A, B;
	wire[7:0] P;
	reg[7:0] P_ref;
	mult_fast mult(P, A, B, clock);
	always @(posedge clock)
		// Originally we have 20 ticks delay, and the clock cycle is 10 ticks, so we have 2 clock cycles delay
		// After changing the clock cycle to 8 ticks, for 2 clock cycles delay, we can reduce to 16 ticks delay
		P_ref <= #16 A*B;		
	// loop through all possible inputs
	integer i;
	initial begin
		#7;
		for(i=0; i<256; i=i+1) begin
			{A, B} <= i;
			#8;		// After every one clock cycle, we can add a new input 
		end
		#17 $finish;
	end
	// check if the products are correct
	reg[3:0] A_old, B_old;
	always @(posedge clock) begin
		#1
		if(P_ref!=P && i>=2) begin
			A_old = (i-2)/16;
			B_old = (i-2)%16;
			$display("Product is wrong when A=%b, B=%b.", A_old, B_old);
			$display("P_ref: %b.", P_ref);
			$display("P    : %b.", P);
			#7 $finish;
		end
	end
endmodule

HW4/LAB-02/lab2.vcd
$date
	Sun May 18 22:42:39 2025
$end
$version
	Icarus Verilog
$end
$timescale
	1s
$end
$scope module mult_tb $end
$var wire 8 ! P [7:0] $end
$var reg 4 " A [3:0] $end
$var reg 4 # A_old [3:0] $end
$var reg 4 $ B [3:0] $end
$var reg 4 % B_old [3:0] $end
$var reg 8 & P_ref [7:0] $end
$var reg 1 ' clock $end
$var integer 32 ( i [31:0] $end
$scope module mult $end
$var wire 4 ) A [3:0] $end
$var wire 4 * B [3:0] $end
$var wire 1 ' clk $end
$var wire 4 + pp0 [3:0] $end
$var wire 4 , pp1 [4:1] $end
$var wire 4 - pp2 [5:2] $end
$var wire 4 . pp3 [6:3] $end
$var reg 8 / P [7:0] $end
$var reg 4 0 a_s0 [3:0] $end
$var reg 4 1 b_s0 [3:0] $end
$var reg 5 2 sum1 [5:1] $end
$var reg 6 3 sum1_s1 [5:0] $end
$var reg 6 4 sum2 [7:2] $end
$var reg 5 5 sum3 [7:3] $end
$var reg 6 6 sum3_s1 [7:2] $end
$upscope $end
$upscope $end
$enddefinitions $end
$comment Show the parameter values. $end
$dumpall
$end
#0
$dumpvars
bx 6
bx 5
bx 4
bx 3
bx 2
bx 1
bx 0
bx /
bx .
bx -
bx ,
bx +
bx *
bx )
bx (
1'
bx &
bx %
bx $
bx #
bx "
bx !
$end
#4
0'
#7
b0 "
b0 )
b0 $
b0 *
b0 (
#8
b0 .
b0 -
b0 ,
b0 +
b0 1
b0 0
1'
#12
0'
#15
b1 $
b1 *
b0 5
b0 2
b1 (
#16
b1 1
b0 6
b0 3
1'
#20
0'
#23
b10 $
b10 *
b10 (
#24
b0 !
b0 /
b10 1
1'
b0 4
b0 &
#28
0'
#31
b11 $
b11 *
b11 (
#32
b11 1
1'
#36
0'
#39
b100 $
b100 *
b100 (
#40
b100 1
1'
#44
0'
#47
b101 $
b101 *
b101 (
#48
b101 1
1'
#52
0'
#55
b110 $
b110 *
b110 (
#56
b110 1
1'
#60
0'
#63
b111 $
b111 *
b111 (
#64
b111 1
1'
#68
0'
#71
b1000 $
b1000 *
b1000 (
#72
b1000 1
1'
#76
0'
#79
b1001 $
b1001 *
b1001 (
#80
b1001 1
1'
#84
0'
#87
b1010 $
b1010 *
b1010 (
#88
b1010 1
1'
#92
0'
#95
b1011 $
b1011 *
b1011 (
#96
b1011 1
1'
#100
0'
#103
b1100 $
b1100 *
b1100 (
#104
b1100 1
1'
#108
0'
#111
b1101 $
b1101 *
b1101 (
#112
b1101 1
1'
#116
0'
#119
b1110 $
b1110 *
b1110 (
#120
b1110 1
1'
#124
0'
#127
b1111 $
b1111 *
b1111 (
#128
b1111 1
1'
#132
0'
#135
b1 "
b1 )
b0 $
b0 *
b10000 (
#136
b0 .
b0 -
b0 ,
b0 +
b0 1
b1 0
1'
#140
0'
#143
b1 $
b1 *
b0 5
b0 2
b10001 (
#144
b1 +
b1 1
1'
#148
0'
#151
b10 $
b10 *
b10010 (
#152
b0 +
b1 ,
b1 3
b10 1
1'
#156
0'
#159
b11 $
b11 *
b1 2
b10011 (
#160
b1 +
b11 1
b10 3
b1 !
b1 /
1'
b1 &
#164
0'
#167
b100 $
b100 *
b10100 (
#168
b0 +
b0 ,
b1 -
b10 !
b10 /
b11 3
b100 1
1'
b10 &
#172
0'
#175
b101 $
b101 *
b0 2
b10101 (
#176
b1 +
b101 1
b1 6
b0 3
b11 !
b11 /
1'
b11 &
#180
0'
#183
b110 $
b110 *
b10110 (
#184
b0 +
b1 ,
b100 !
b100 /
b1 3
b110 1
1'
b1 4
b100 &
#188
0'
#191
b111 $
b111 *
b1 2
b10111 (
#192
b1 +
b111 1
b10 3
b101 !
b101 /
1'
b101 &
#196
0'
#199
b1000 $
b1000 *
b11000 (
#200
b0 +
b0 ,
b0 -
b1 .
b110 !
b110 /
b11 3
b1000 1
1'
b110 &
#204
0'
#207
b1001 $
b1001 *
b0 2
b1 5
b11001 (
#208
b1 +
b1001 1
b10 6
b0 3
b111 !
b111 /
1'
b111 &
#212
0'
#215
b1010 $
b1010 *
b11010 (
#216
b0 +
b1 ,
b1000 !
b1000 /
b1 3
b1010 1
1'
b10 4
b1000 &
#220
0'
#223
b1011 $
b1011 *
b1 2
b11011 (
#224
b1 +
b1011 1
b10 3
b1001 !
b1001 /
1'
b1001 &
#228
0'
#231
b1100 $
b1100 *
b11100 (
#232
b0 +
b0 ,
b1 -
b1010 !
b1010 /
b11 3
b1100 1
1'
b1010 &
#236
0'
#239
b1101 $
b1101 *
b0 2
b11101 (
#240
b1 +
b1101 1
b11 6
b0 3
b1011 !
b1011 /
1'
b1011 &
#244
0'
#247
b1110 $
b1110 *
b11110 (
#248
b0 +
b1 ,
b1100 !
b1100 /
b1 3
b1110 1
1'
b11 4
b1100 &
#252
0'
#255
b1111 $
b1111 *
b1 2
b11111 (
#256
b1 +
b1111 1
b10 3
b1101 !
b1101 /
1'
b1101 &
#260
0'
#263
b10 "
b10 )
b0 $
b0 *
b100000 (
#264
b0 .
b0 -
b0 ,
b0 +
b1110 !
b1110 /
b11 3
b0 1
b10 0
1'
b1110 &
#268
0'
#271
b1 $
b1 *
b0 5
b0 2
b100001 (
#272
b10 +
b1 1
b0 6
b0 3
b1111 !
b1111 /
1'
b1111 &
#276
0'
#279
b10 $
b10 *
b1 2
b100010 (
#280
b0 +
b10 ,
b0 !
b0 /
b10 3
b10 1
1'
b0 4
b0 &
#284
0'
#287
b11 $
b11 *
b10 2
b100011 (
#288
b10 +
b11 1
b100 3
b10 !
b10 /
1'
b10 &
#292
0'
#295
b100 $
b100 *
b11 2
b100100 (
#296
b0 +
b0 ,
b10 -
b100 !
b100 /
b110 3
b100 1
1'
b1 4
b100 &
#300
0'
#303
b101 $
b101 *
b0 2
b1 5
b100101 (
#304
b10 +
b101 1
b10 6
b0 3
b110 !
b110 /
1'
b110 &
#308
0'
#311
b110 $
b110 *
b1 2
b100110 (
#312
b0 +
b10 ,
b1000 !
b1000 /
b10 3
b110 1
1'
b10 4
b1000 &
#316
0'
#319
b111 $
b111 *
b10 2
b100111 (
#320
b10 +
b111 1
b100 3
b1010 !
b1010 /
1'
b1010 &
#324
0'
#327
b1000 $
b1000 *
b11 2
b101000 (
#328
b0 +
b0 ,
b0 -
b10 .
b1100 !
b1100 /
b110 3
b1000 1
1'
b11 4
b1100 &
#332
0'
#335
b1001 $
b1001 *
b0 2
b10 5
b101001 (
#336
b10 +
b1001 1
b100 6
b0 3
b1110 !
b1110 /
1'
b1110 &
#340
0'
#343
b1010 $
b1010 *
b1 2
b101010 (
#344
b0 +
b10 ,
b10000 !
b10000 /
b10 3
b1010 1
1'
b100 4
b10000 &
#348
0'
#351
b1011 $
b1011 *
b10 2
b101011 (
#352
b10 +
b1011 1
b100 3
b10010 !
b10010 /
1'
b10010 &
#356
0'
#359
b1100 $
b1100 *
b11 2
b101100 (
#360
b0 +
b0 ,
b10 -
b10100 !
b10100 /
b110 3
b1100 1
1'
b101 4
b10100 &
#364
0'
#367
b1101 $
b1101 *
b0 2
b11 5
b101101 (
#368
b10 +
b1101 1
b110 6
b0 3
b10110 !
b10110 /
1'
b10110 &
#372
0'
#375
b1110 $
b1110 *
b1 2
b101110 (
#376
b0 +
b10 ,
b11000 !
b11000 /
b10 3
b1110 1
1'
b110 4
b11000 &
#380
0'
#383
b1111 $
b1111 *
b10 2
b101111 (
#384
b10 +
b1111 1
b100 3
b11010 !
b11010 /
1'
b11010 &
#388
0'
#391
b11 "
b11 )
b0 $
b0 *
b11 2
b110000 (
#392
b0 .
b0 -
b0 ,
b0 +
b11100 !
b11100 /
b110 3
b0 1
b11 0
1'
b111 4
b11100 &
#396
0'
#399
b1 $
b1 *
b0 5
b0 2
b110001 (
#400
b11 +
b1 1
b0 6
b0 3
b11110 !
b11110 /
1'
b11110 &
#404
0'
#407
b10 $
b10 *
b1 2
b110010 (
#408
b0 +
b11 ,
b0 !
b0 /
b11 3
b10 1
1'
b0 4
b0 &
#412
0'
#415
b11 $
b11 *
b11 2
b110011 (
#416
b11 +
b11 1
b110 3
b11 !
b11 /
1'
b11 &
#420
0'
#423
b100 $
b100 *
b100 2
b110100 (
#424
b0 +
b0 ,
b11 -
b110 !
b110 /
b1001 3
b100 1
1'
b1 4
b110 &
#428
0'
#431
b101 $
b101 *
b0 2
b1 5
b110101 (
#432
b11 +
b101 1
b11 6
b0 3
b1001 !
b1001 /
1'
b10 4
b1001 &
#436
0'
#439
b110 $
b110 *
b1 2
b110110 (
#440
b0 +
b11 ,
b1100 !
b1100 /
b11 3
b110 1
1'
b11 4
b1100 &
#444
0'
#447
b111 $
b111 *
b11 2
b110111 (
#448
b11 +
b111 1
b110 3
b1111 !
b1111 /
1'
b1111 &
#452
0'
#455
b1000 $
b1000 *
b100 2
b111000 (
#456
b0 +
b0 ,
b0 -
b11 .
b10010 !
b10010 /
b1001 3
b1000 1
1'
b100 4
b10010 &
#460
0'
#463
b1001 $
b1001 *
b0 2
b11 5
b111001 (
#464
b11 +
b1001 1
b110 6
b0 3
b10101 !
b10101 /
1'
b101 4
b10101 &
#468
0'
#471
b1010 $
b1010 *
b1 2
b111010 (
#472
b0 +
b11 ,
b11000 !
b11000 /
b11 3
b1010 1
1'
b110 4
b11000 &
#476
0'
#479
b1011 $
b1011 *
b11 2
b111011 (
#480
b11 +
b1011 1
b110 3
b11011 !
b11011 /
1'
b11011 &
#484
0'
#487
b1100 $
b1100 *
b100 2
b111100 (
#488
b0 +
b0 ,
b11 -
b11110 !
b11110 /
b1001 3
b1100 1
1'
b111 4
b11110 &
#492
0'
#495
b1101 $
b1101 *
b0 2
b100 5
b111101 (
#496
b11 +
b1101 1
b1001 6
b0 3
b100001 !
b100001 /
1'
b1000 4
b100001 &
#500
0'
#503
b1110 $
b1110 *
b1 2
b111110 (
#504
b0 +
b11 ,
b100100 !
b100100 /
b11 3
b1110 1
1'
b1001 4
b100100 &
#508
0'
#511
b1111 $
b1111 *
b11 2
b111111 (
#512
b11 +
b1111 1
b110 3
b100111 !
b100111 /
1'
b100111 &
#516
0'
#519
b100 "
b100 )
b0 $
b0 *
b100 2
b1000000 (
#520
b0 .
b0 -
b0 ,
b0 +
b101010 !
b101010 /
b1001 3
b0 1
b100 0
1'
b1010 4
b101010 &
#524
0'
#527
b1 $
b1 *
b0 5
b0 2
b1000001 (
#528
b100 +
b1 1
b0 6
b0 3
b101101 !
b101101 /
1'
b1011 4
b101101 &
#532
0'
#535
b10 $
b10 *
b10 2
b1000010 (
#536
b0 +
b100 ,
b0 !
b0 /
b100 3
b10 1
1'
b0 4
b0 &
#540
0'
#543
b11 $
b11 *
b100 2
b1000011 (
#544
b100 +
b11 1
b1000 3
b100 !
b100 /
1'
b1 4
b100 &
#548
0'
#551
b100 $
b100 *
b110 2
b1000100 (
#552
b0 +
b0 ,
b100 -
b1000 !
b1000 /
b1100 3
b100 1
1'
b10 4
b1000 &
#556
0'
#559
b101 $
b101 *
b0 2
b10 5
b1000101 (
#560
b100 +
b101 1
b100 6
b0 3
b1100 !
b1100 /
1'
b11 4
b1100 &
#564
0'
#567
b110 $
b110 *
b10 2
b1000110 (
#568
b0 +
b100 ,
b10000 !
b10000 /
b100 3
b110 1
1'
b100 4
b10000 &
#572
0'
#575
b111 $
b111 *
b100 2
b1000111 (
#576
b100 +
b111 1
b1000 3
b10100 !
b10100 /
1'
b101 4
b10100 &
#580
0'
#583
b1000 $
b1000 *
b110 2
b1001000 (
#584
b0 +
b0 ,
b0 -
b100 .
b11000 !
b11000 /
b1100 3
b1000 1
1'
b110 4
b11000 &
#588
0'
#591
b1001 $
b1001 *
b0 2
b100 5
b1001001 (
#592
b100 +
b1001 1
b1000 6
b0 3
b11100 !
b11100 /
1'
b111 4
b11100 &
#596
0'
#599
b1010 $
b1010 *
b10 2
b1001010 (
#600
b0 +
b100 ,
b100000 !
b100000 /
b100 3
b1010 1
1'
b1000 4
b100000 &
#604
0'
#607
b1011 $
b1011 *
b100 2
b1001011 (
#608
b100 +
b1011 1
b1000 3
b100100 !
b100100 /
1'
b1001 4
b100100 &
#612
0'
#615
b1100 $
b1100 *
b110 2
b1001100 (
#616
b0 +
b0 ,
b100 -
b101000 !
b101000 /
b1100 3
b1100 1
1'
b1010 4
b101000 &
#620
0'
#623
b1101 $
b1101 *
b0 2
b110 5
b1001101 (
#624
b100 +
b1101 1
b1100 6
b0 3
b101100 !
b101100 /
1'
b1011 4
b101100 &
#628
0'
#631
b1110 $
b1110 *
b10 2
b1001110 (
#632
b0 +
b100 ,
b110000 !
b110000 /
b100 3
b1110 1
1'
b1100 4
b110000 &
#636
0'
#639
b1111 $
b1111 *
b100 2
b1001111 (
#640
b100 +
b1111 1
b1000 3
b110100 !
b110100 /
1'
b1101 4
b110100 &
#644
0'
#647
b101 "
b101 )
b0 $
b0 *
b110 2
b1010000 (
#648
b0 .
b0 -
b0 ,
b0 +
b111000 !
b111000 /
b1100 3
b0 1
b101 0
1'
b1110 4
b111000 &
#652
0'
#655
b1 $
b1 *
b0 5
b0 2
b1010001 (
#656
b101 +
b1 1
b0 6
b0 3
b111100 !
b111100 /
1'
b1111 4
b111100 &
#660
0'
#663
b10 $
b10 *
b10 2
b1010010 (
#664
b0 +
b101 ,
b0 !
b0 /
b101 3
b10 1
1'
b0 4
b0 &
#668
0'
#671
b11 $
b11 *
b101 2
b1010011 (
#672
b101 +
b11 1
b1010 3
b101 !
b101 /
1'
b1 4
b101 &
#676
0'
#679
b100 $
b100 *
b111 2
b1010100 (
#680
b0 +
b0 ,
b101 -
b1010 !
b1010 /
b1111 3
b100 1
1'
b10 4
b1010 &
#684
0'
#687
b101 $
b101 *
b0 2
b10 5
b1010101 (
#688
b101 +
b101 1
b101 6
b0 3
b1111 !
b1111 /
1'
b11 4
b1111 &
#692
0'
#695
b110 $
b110 *
b10 2
b1010110 (
#696
b0 +
b101 ,
b10100 !
b10100 /
b101 3
b110 1
1'
b101 4
b10100 &
#700
0'
#703
b111 $
b111 *
b101 2
b1010111 (
#704
b101 +
b111 1
b1010 3
b11001 !
b11001 /
1'
b110 4
b11001 &
#708
0'
#711
b1000 $
b1000 *
b111 2
b1011000 (
#712
b0 +
b0 ,
b0 -
b101 .
b11110 !
b11110 /
b1111 3
b1000 1
1'
b111 4
b11110 &
#716
0'
#719
b1001 $
b1001 *
b0 2
b101 5
b1011001 (
#720
b101 +
b1001 1
b1010 6
b0 3
b100011 !
b100011 /
1'
b1000 4
b100011 &
#724
0'
#727
b1010 $
b1010 *
b10 2
b1011010 (
#728
b0 +
b101 ,
b101000 !
b101000 /
b101 3
b1010 1
1'
b1010 4
b101000 &
#732
0'
#735
b1011 $
b1011 *
b101 2
b1011011 (
#736
b101 +
b1011 1
b1010 3
b101101 !
b101101 /
1'
b1011 4
b101101 &
#740
0'
#743
b1100 $
b1100 *
b111 2
b1011100 (
#744
b0 +
b0 ,
b101 -
b110010 !
b110010 /
b1111 3
b1100 1
1'
b1100 4
b110010 &
#748
0'
#751
b1101 $
b1101 *
b0 2
b111 5
b1011101 (
#752
b101 +
b1101 1
b1111 6
b0 3
b110111 !
b110111 /
1'
b1101 4
b110111 &
#756
0'
#759
b1110 $
b1110 *
b10 2
b1011110 (
#760
b0 +
b101 ,
b111100 !
b111100 /
b101 3
b1110 1
1'
b1111 4
b111100 &
#764
0'
#767
b1111 $
b1111 *
b101 2
b1011111 (
#768
b101 +
b1111 1
b1010 3
b1000001 !
b1000001 /
1'
b10000 4
b1000001 &
#772
0'
#775
b110 "
b110 )
b0 $
b0 *
b111 2
b1100000 (
#776
b0 .
b0 -
b0 ,
b0 +
b1000110 !
b1000110 /
b1111 3
b0 1
b110 0
1'
b10001 4
b1000110 &
#780
0'
#783
b1 $
b1 *
b0 5
b0 2
b1100001 (
#784
b110 +
b1 1
b0 6
b0 3
b1001011 !
b1001011 /
1'
b10010 4
b1001011 &
#788
0'
#791
b10 $
b10 *
b11 2
b1100010 (
#792
b0 +
b110 ,
b0 !
b0 /
b110 3
b10 1
1'
b0 4
b0 &
#796
0'
#799
b11 $
b11 *
b110 2
b1100011 (
#800
b110 +
b11 1
b1100 3
b110 !
b110 /
1'
b1 4
b110 &
#804
0'
#807
b100 $
b100 *
b1001 2
b1100100 (
#808
b0 +
b0 ,
b110 -
b1100 !
b1100 /
b10010 3
b100 1
1'
b11 4
b1100 &
#812
0'
#815
b101 $
b101 *
b0 2
b11 5
b1100101 (
#816
b110 +
b101 1
b110 6
b0 3
b10010 !
b10010 /
1'
b100 4
b10010 &
#820
0'
#823
b110 $
b110 *
b11 2
b1100110 (
#824
b0 +
b110 ,
b11000 !
b11000 /
b110 3
b110 1
1'
b110 4
b11000 &
#828
0'
#831
b111 $
b111 *
b110 2
b1100111 (
#832
b110 +
b111 1
b1100 3
b11110 !
b11110 /
1'
b111 4
b11110 &
#836
0'
#839
b1000 $
b1000 *
b1001 2
b1101000 (
#840
b0 +
b0 ,
b0 -
b110 .
b100100 !
b100100 /
b10010 3
b1000 1
1'
b1001 4
b100100 &
#844
0'
#847
b1001 $
b1001 *
b0 2
b110 5
b1101001 (
#848
b110 +
b1001 1
b1100 6
b0 3
b101010 !
b101010 /
1'
b1010 4
b101010 &
#852
0'
#855
b1010 $
b1010 *
b11 2
b1101010 (
#856
b0 +
b110 ,
b110000 !
b110000 /
b110 3
b1010 1
1'
b1100 4
b110000 &
#860
0'
#863
b1011 $
b1011 *
b110 2
b1101011 (
#864
b110 +
b1011 1
b1100 3
b110110 !
b110110 /
1'
b1101 4
b110110 &
#868
0'
#871
b1100 $
b1100 *
b1001 2
b1101100 (
#872
b0 +
b0 ,
b110 -
b111100 !
b111100 /
b10010 3
b1100 1
1'
b1111 4
b111100 &
#876
0'
#879
b1101 $
b1101 *
b0 2
b1001 5
b1101101 (
#880
b110 +
b1101 1
b10010 6
b0 3
b1000010 !
b1000010 /
1'
b10000 4
b1000010 &
#884
0'
#887
b1110 $
b1110 *
b11 2
b1101110 (
#888
b0 +
b110 ,
b1001000 !
b1001000 /
b110 3
b1110 1
1'
b10010 4
b1001000 &
#892
0'
#895
b1111 $
b1111 *
b110 2
b1101111 (
#896
b110 +
b1111 1
b1100 3
b1001110 !
b1001110 /
1'
b10011 4
b1001110 &
#900
0'
#903
b111 "
b111 )
b0 $
b0 *
b1001 2
b1110000 (
#904
b0 .
b0 -
b0 ,
b0 +
b1010100 !
b1010100 /
b10010 3
b0 1
b111 0
1'
b10101 4
b1010100 &
#908
0'
#911
b1 $
b1 *
b0 5
b0 2
b1110001 (
#912
b111 +
b1 1
b0 6
b0 3
b1011010 !
b1011010 /
1'
b10110 4
b1011010 &
#916
0'
#919
b10 $
b10 *
b11 2
b1110010 (
#920
b0 +
b111 ,
b0 !
b0 /
b111 3
b10 1
1'
b0 4
b0 &
#924
0'
#927
b11 $
b11 *
b111 2
b1110011 (
#928
b111 +
b11 1
b1110 3
b111 !
b111 /
1'
b1 4
b111 &
#932
0'
#935
b100 $
b100 *
b1010 2
b1110100 (
#936
b0 +
b0 ,
b111 -
b1110 !
b1110 /
b10101 3
b100 1
1'
b11 4
b1110 &
#940
0'
#943
b101 $
b101 *
b0 2
b11 5
b1110101 (
#944
b111 +
b101 1
b111 6
b0 3
b10101 !
b10101 /
1'
b101 4
b10101 &
#948
0'
#951
b110 $
b110 *
b11 2
b1110110 (
#952
b0 +
b111 ,
b11100 !
b11100 /
b111 3
b110 1
1'
b111 4
b11100 &
#956
0'
#959
b111 $
b111 *
b111 2
b1110111 (
#960
b111 +
b111 1
b1110 3
b100011 !
b100011 /
1'
b1000 4
b100011 &
#964
0'
#967
b1000 $
b1000 *
b1010 2
b1111000 (
#968
b0 +
b0 ,
b0 -
b111 .
b101010 !
b101010 /
b10101 3
b1000 1
1'
b1010 4
b101010 &
#972
0'
#975
b1001 $
b1001 *
b0 2
b111 5
b1111001 (
#976
b111 +
b1001 1
b1110 6
b0 3
b110001 !
b110001 /
1'
b1100 4
b110001 &
#980
0'
#983
b1010 $
b1010 *
b11 2
b1111010 (
#984
b0 +
b111 ,
b111000 !
b111000 /
b111 3
b1010 1
1'
b1110 4
b111000 &
#988
0'
#991
b1011 $
b1011 *
b111 2
b1111011 (
#992
b111 +
b1011 1
b1110 3
b111111 !
b111111 /
1'
b1111 4
b111111 &
#996
0'
#999
b1100 $
b1100 *
b1010 2
b1111100 (
#1000
b0 +
b0 ,
b111 -
b1000110 !
b1000110 /
b10101 3
b1100 1
1'
b10001 4
b1000110 &
#1004
0'
#1007
b1101 $
b1101 *
b0 2
b1010 5
b1111101 (
#1008
b111 +
b1101 1
b10101 6
b0 3
b1001101 !
b1001101 /
1'
b10011 4
b1001101 &
#1012
0'
#1015
b1110 $
b1110 *
b11 2
b1111110 (
#1016
b0 +
b111 ,
b1010100 !
b1010100 /
b111 3
b1110 1
1'
b10101 4
b1010100 &
#1020
0'
#1023
b1111 $
b1111 *
b111 2
b1111111 (
#1024
b111 +
b1111 1
b1110 3
b1011011 !
b1011011 /
1'
b10110 4
b1011011 &
#1028
0'
#1031
b1000 "
b1000 )
b0 $
b0 *
b1010 2
b10000000 (
#1032
b0 .
b0 -
b0 ,
b0 +
b1100010 !
b1100010 /
b10101 3
b0 1
b1000 0
1'
b11000 4
b1100010 &
#1036
0'
#1039
b1 $
b1 *
b0 5
b0 2
b10000001 (
#1040
b1000 +
b1 1
b0 6
b0 3
b1101001 !
b1101001 /
1'
b11010 4
b1101001 &
#1044
0'
#1047
b10 $
b10 *
b100 2
b10000010 (
#1048
b0 +
b1000 ,
b0 !
b0 /
b1000 3
b10 1
1'
b0 4
b0 &
#1052
0'
#1055
b11 $
b11 *
b1000 2
b10000011 (
#1056
b1000 +
b11 1
b10000 3
b1000 !
b1000 /
1'
b10 4
b1000 &
#1060
0'
#1063
b100 $
b100 *
b1100 2
b10000100 (
#1064
b0 +
b0 ,
b1000 -
b10000 !
b10000 /
b11000 3
b100 1
1'
b100 4
b10000 &
#1068
0'
#1071
b101 $
b101 *
b0 2
b100 5
b10000101 (
#1072
b1000 +
b101 1
b1000 6
b0 3
b11000 !
b11000 /
1'
b110 4
b11000 &
#1076
0'
#1079
b110 $
b110 *
b100 2
b10000110 (
#1080
b0 +
b1000 ,
b100000 !
b100000 /
b1000 3
b110 1
1'
b1000 4
b100000 &
#1084
0'
#1087
b111 $
b111 *
b1000 2
b10000111 (
#1088
b1000 +
b111 1
b10000 3
b101000 !
b101000 /
1'
b1010 4
b101000 &
#1092
0'
#1095
b1000 $
b1000 *
b1100 2
b10001000 (
#1096
b0 +
b0 ,
b0 -
b1000 .
b110000 !
b110000 /
b11000 3
b1000 1
1'
b1100 4
b110000 &
#1100
0'
#1103
b1001 $
b1001 *
b0 2
b1000 5
b10001001 (
#1104
b1000 +
b1001 1
b10000 6
b0 3
b111000 !
b111000 /
1'
b1110 4
b111000 &
#1108
0'
#1111
b1010 $
b1010 *
b100 2
b10001010 (
#1112
b0 +
b1000 ,
b1000000 !
b1000000 /
b1000 3
b1010 1
1'
b10000 4
b1000000 &
#1116
0'
#1119
b1011 $
b1011 *
b1000 2
b10001011 (
#1120
b1000 +
b1011 1
b10000 3
b1001000 !
b1001000 /
1'
b10010 4
b1001000 &
#1124
0'
#1127
b1100 $
b1100 *
b1100 2
b10001100 (
#1128
b0 +
b0 ,
b1000 -
b1010000 !
b1010000 /
b11000 3
b1100 1
1'
b10100 4
b1010000 &
#1132
0'
#1135
b1101 $
b1101 *
b0 2
b1100 5
b10001101 (
#1136
b1000 +
b1101 1
b11000 6
b0 3
b1011000 !
b1011000 /
1'
b10110 4
b1011000 &
#1140
0'
#1143
b1110 $
b1110 *
b100 2
b10001110 (
#1144
b0 +
b1000 ,
b1100000 !
b1100000 /
b1000 3
b1110 1
1'
b11000 4
b1100000 &
#1148
0'
#1151
b1111 $
b1111 *
b1000 2
b10001111 (
#1152
b1000 +
b1111 1
b10000 3
b1101000 !
b1101000 /
1'
b11010 4
b1101000 &
#1156
0'
#1159
b1001 "
b1001 )
b0 $
b0 *
b1100 2
b10010000 (
#1160
b0 .
b0 -
b0 ,
b0 +
b1110000 !
b1110000 /
b11000 3
b0 1
b1001 0
1'
b11100 4
b1110000 &
#1164
0'
#1167
b1 $
b1 *
b0 5
b0 2
b10010001 (
#1168
b1001 +
b1 1
b0 6
b0 3
b1111000 !
b1111000 /
1'
b11110 4
b1111000 &
#1172
0'
#1175
b10 $
b10 *
b100 2
b10010010 (
#1176
b0 +
b1001 ,
b0 !
b0 /
b1001 3
b10 1
1'
b0 4
b0 &
#1180
0'
#1183
b11 $
b11 *
b1001 2
b10010011 (
#1184
b1001 +
b11 1
b10010 3
b1001 !
b1001 /
1'
b10 4
b1001 &
#1188
0'
#1191
b100 $
b100 *
b1101 2
b10010100 (
#1192
b0 +
b0 ,
b1001 -
b10010 !
b10010 /
b11011 3
b100 1
1'
b100 4
b10010 &
#1196
0'
#1199
b101 $
b101 *
b0 2
b100 5
b10010101 (
#1200
b1001 +
b101 1
b1001 6
b0 3
b11011 !
b11011 /
1'
b110 4
b11011 &
#1204
0'
#1207
b110 $
b110 *
b100 2
b10010110 (
#1208
b0 +
b1001 ,
b100100 !
b100100 /
b1001 3
b110 1
1'
b1001 4
b100100 &
#1212
0'
#1215
b111 $
b111 *
b1001 2
b10010111 (
#1216
b1001 +
b111 1
b10010 3
b101101 !
b101101 /
1'
b1011 4
b101101 &
#1220
0'
#1223
b1000 $
b1000 *
b1101 2
b10011000 (
#1224
b0 +
b0 ,
b0 -
b1001 .
b110110 !
b110110 /
b11011 3
b1000 1
1'
b1101 4
b110110 &
#1228
0'
#1231
b1001 $
b1001 *
b0 2
b1001 5
b10011001 (
#1232
b1001 +
b1001 1
b10010 6
b0 3
b111111 !
b111111 /
1'
b1111 4
b111111 &
#1236
0'
#1239
b1010 $
b1010 *
b100 2
b10011010 (
#1240
b0 +
b1001 ,
b1001000 !
b1001000 /
b1001 3
b1010 1
1'
b10010 4
b1001000 &
#1244
0'
#1247
b1011 $
b1011 *
b1001 2
b10011011 (
#1248
b1001 +
b1011 1
b10010 3
b1010001 !
b1010001 /
1'
b10100 4
b1010001 &
#1252
0'
#1255
b1100 $
b1100 *
b1101 2
b10011100 (
#1256
b0 +
b0 ,
b1001 -
b1011010 !
b1011010 /
b11011 3
b1100 1
1'
b10110 4
b1011010 &
#1260
0'
#1263
b1101 $
b1101 *
b0 2
b1101 5
b10011101 (
#1264
b1001 +
b1101 1
b11011 6
b0 3
b1100011 !
b1100011 /
1'
b11000 4
b1100011 &
#1268
0'
#1271
b1110 $
b1110 *
b100 2
b10011110 (
#1272
b0 +
b1001 ,
b1101100 !
b1101100 /
b1001 3
b1110 1
1'
b11011 4
b1101100 &
#1276
0'
#1279
b1111 $
b1111 *
b1001 2
b10011111 (
#1280
b1001 +
b1111 1
b10010 3
b1110101 !
b1110101 /
1'
b11101 4
b1110101 &
#1284
0'
#1287
b1010 "
b1010 )
b0 $
b0 *
b1101 2
b10100000 (
